laureate/LICENSE.md
laureate/__init__.py
laureate/laureate.py
laureate/templates.py
laureate/util.py
laureate-3.0.0.dist-info/entry_points.txt
laureate-3.0.0.dist-info/LICENSE.md
laureate-3.0.0.dist-info/METADATA
laureate-3.0.0.dist-info/WHEEL
laureate-3.0.0.dist-info/RECORD
